{
  "version": "7",
  "dialect": "postgresql",
  "entries": [
    {
      "idx": 0,
      "version": "7",
      "when": 1768768038706,
      "tag": "0000_mute_jackal",
      "breakpoints": true
    },
    {
      "idx": 1,
      "version": "7",
      "when": 1771774808192,
      "tag": "0001_greedy_tiger_shark",
      "breakpoints": true
    },
    {
      "idx": 2,
      "version": "7",
      "when": 1772127102657,
      "tag": "0002_certain_chat",
      "breakpoints": true
    },
    {
      "idx": 3,
      "version": "7",
      "when": 1772145552129,
      "tag": "0003_luxuriant_true_believers",
      "breakpoints": true
    }
  ]
}
